semantic_routing_memory-1.0.1.dist-info/licenses/LICENSE
srmem/__init__.py
srmem/srm.py
semantic_routing_memory-1.0.1.dist-info/METADATA
semantic_routing_memory-1.0.1.dist-info/WHEEL
semantic_routing_memory-1.0.1.dist-info/top_level.txt
semantic_routing_memory-1.0.1.dist-info/RECORD
