Metadata-Version: 2.4
Name: semantic-routing-memory
Version: 1.0.1
Summary: A lightweight, sustainable long-term memory layer for agentic AI systems using vector quantization
Author: Ahmet Yiğit Sertel
License: MIT
Project-URL: Homepage, https://github.com/AhmetYSertel/Semantic-Routing-Memory-System
Project-URL: Documentation, https://github.com/AhmetYSertel/Semantic-Routing-Memory-System#readme
Project-URL: Repository, https://github.com/AhmetYSertel/Semantic-Routing-Memory-System
Project-URL: Issues, https://github.com/AhmetYSertel/Semantic-Routing-Memory-System/issues
Keywords: memory,vector-quantization,semantic-routing,llm,agents,rag,long-term-memory
Classifier: Development Status :: 4 - Beta
Classifier: Intended Audience :: Developers
Classifier: Intended Audience :: Science/Research
Classifier: License :: OSI Approved :: MIT License
Classifier: Operating System :: OS Independent
Classifier: Programming Language :: Python :: 3
Classifier: Programming Language :: Python :: 3.9
Classifier: Programming Language :: Python :: 3.10
Classifier: Programming Language :: Python :: 3.11
Classifier: Programming Language :: Python :: 3.12
Classifier: Programming Language :: Python :: 3.13
Classifier: Topic :: Scientific/Engineering :: Artificial Intelligence
Requires-Python: >=3.9
License-File: LICENSE
Requires-Dist: numpy>=1.24
Provides-Extra: dev
Requires-Dist: pytest>=7.0; extra == "dev"
Requires-Dist: pytest-cov>=4.0; extra == "dev"
Dynamic: license-file
